Workbook

Sheet Backlog
A1: Slice | B1: Milestone | C1: ID | D1: Epic | E1: Task | F1: Description | G1: Est (days) | H1: Depends on | I1: Sprint | J1: Priority | K1: Acceptance | L1: Status
A2: 0 | B2: Spine | C2: T1.1 | D2: 1 Supabase backend | E2: Create Supabase project + dev env | F2: Spin up project; configure env keys; install Supabase CLI; set up migrations folder. | G2: 0.5 | H2: - | I2: A: Foundations | J2: P0 | K2: Prereq for AC3 | L2: Not started
A3: 0 | B3: Spine | C3: T1.2 | D3: 1 Supabase backend | E3: Run Wave-1 schema | F3: Apply vamo_wave1_schema.sql; verify tables, trip_balances view, is_trip_member() + join_trip() created. | G3: 0.5 | H3: T1.1 | I3: A: Foundations | J3: P0 | K3: AC3 | L3: Not started
A4: 0 | B4: Spine | C4: T1.3 | D4: 1 Supabase backend | E4: Configure auth providers | F4: Enable email, Apple, Google, phone sign-in. | G4: 1 | H4: T1.1 | I4: A: Foundations | J4: P0 | K4: Screen 1 | L4: Not started
A5: 0 | B5: Spine | C5: T1.4 | D5: 1 Supabase backend | E5: Profile-creation trigger | F5: On signup, trigger inserts profiles row; verify it fires. | G5: 0.5 | H5: T1.2;T1.3 | I5: A: Foundations | J5: P0 | K5: Screen 1 | L5: Not started
A6: 0 | B6: Spine | C6: T1.6 | D6: 1 Supabase backend | E6: RLS validation pass | F6: Use Supabase RLS tester: confirm a non-member cannot read a trip. | G6: 0.5 | H6: T1.2 | I6: A: Foundations | J6: P0 | K6: AC3 | L6: Not started
A7: 0 | B7: Spine | C7: T2.1 | D7: 2 Flutter app_core | E7: Init Flutter monorepo | F7: Set up app + app_core + feature_split packages (melos). | G7: 0.5 | H7: - | I7: A: Foundations | J7: P0 | K7: Build order step 2 | L7: Not started
A8: 0 | B8: Spine | C8: T2.2 | D8: 2 Flutter app_core | E8: Supabase client + session | F8: Init client; session handling; secure token storage. | G8: 0.5 | H8: T2.1;T1.3 | I8: A: Foundations | J8: P0 | K8: Screen 1 | L8: Not started
A9: 0 | B9: Spine | C9: T2.3 | D9: 2 Flutter app_core | E9: Riverpod + router | F9: Provider scaffolding + go_router navigation. | G9: 0.5 | H9: T2.1 | I9: A: Foundations | J9: P0 | K9: - | L9: Not started
A10: 0 | B10: Spine | C10: T2.4 | D10: 2 Flutter app_core | E10: Design system | F10: Teal/sand theme, typography, core components, 'Si va?' styling. | G10: 1 | H10: T2.1 | I10: A: Foundations | J10: P0 | K10: Brand | L10: Not started
A11: 0 | B11: Spine | C11: T2.6 | D11: 2 Flutter app_core | E11: Analytics + entitlement stub | F11: PostHog wrapper with the 7 events; wire entitlement check stub. | G11: 0.5 | H11: T2.1 | I11: A: Foundations | J11: P0 | K11: AC6 | L11: Not started
A12: 0 | B12: Spine | C12: T2.7 | D12: 2 Flutter app_core | E12: i18n setup | F12: Externalize strings from the start. | G12: 0.5 | H12: T2.1 | I12: A: Foundations | J12: P0 | K12: Non-functional | L12: Not started
A13: 0 | B13: Spine | C13: T3.1 | D13: 3 Auth + trips | E13: Auth / onboarding screen | F13: Continue with Apple/Google/email/phone wired to Supabase. | G13: 1 | H13: T2.2;T2.3;T1.3 | I13: B: Core split flow | J13: P0 | K13: Screen 1; AC1,2 | L13: Not started
... A56: 13 | B56: I18n | C56: T13.6 | D56: 13 I18n readiness | E56: Safe error presentation sweep | F56: showActionError helper in app_core: fires action_failed + shows catalogued message by kind (network/auth/server/unknown); replace ALL raw $e SnackBars and error texts (create trip, add expense, suggest, settings, trip home, join, capture, snapshot, members load); messages from i18n catalogue; debug builds may append sanitized code; lint/test guard that no UI string interpolates an exception. | G56: 0.5 | H56: T13.2 | I56: D: Signals | J56: P0 | K56: Non-functional | L56: Not started
F58: TOTAL effort (P0 + stretch) | G58: =SUM(G2:G56) -> 34.25

Sheet Slice summary
A1: Slice | B1: Milestone | C1: Demo outcome | D1: Tasks | E1: Effort (d) | F1: Cumulative (d)
A2: 0 | B2: Spine | C2: Log in -> empty trips list | D2: T1.1, T1.2, T1.3, T1.4, T1.6, T2.1, T2.2, T2.3, T2.4, T2.6, T2.7, T3.1, T3.2 | E2: =SUMIF(Backlog!A:A,A2,Backlog!G:G) -> 8.5 | F2: =E2 -> 8.5
A3: 1 | B3: Spine | C3: Create trip -> persists -> trip home | D3: T2.5, T3.3, T4.1 | E3: =SUMIF(Backlog!A:A,A3,Backlog!G:G) -> 3 | F3: =F2+E3 -> 11.5
A4: 2 | B4: Spine | C4: EUR30 dinner, equal split | D4: T5.1, T5.2 | E4: =SUMIF(Backlog!A:A,A4,Backlog!G:G) -> 2 | F4: =F3+E4 -> 13.5
A5: 3 | B5: Spine | C5: Who owes whom + tests green | D5: T6.1, T6.2, T6.3 | E5: =SUMIF(Backlog!A:A,A5,Backlog!G:G) -> 2 | F5: =F4+E5 -> 15.5
A6: 4 | B6: Spine | C6: Mark settle -> Venmo -> confirm | D6: T6.4, T6.5 | E6: =SUMIF(Backlog!A:A,A6,Backlog!G:G) -> 1.5 | F6: =F5+E6 -> 17
A7: 5 | B7: Multiplayer | C7: Second phone joins via link | D7: T4.2, T4.3 | E7: =SUMIF(Backlog!A:A,A7,Backlog!G:G) -> 2 | F7: =F6+E7 -> 19
A8: 6 | B8: Growth | C8: $ expense on EUR trip | D8: T1.7, T5.3 | E8: =SUMIF(Backlog!A:A,A8,Backlog!G:G) -> 1 | F8: =F7+E8 -> 20
A9: 7 | B9: Growth | C9: Share branded card | D9: T1.5, T7.1, T7.2 | E9: =SUMIF(Backlog!A:A,A9,Backlog!G:G) -> 2 | F9: =F8+E9 -> 22
A10: 8 | B10: Growth | C10: Solo capture -> snapshot | D10: T8.1 | E10: =SUMIF(Backlog!A:A,A10,Backlog!G:G) -> 1 | F10: =F9+E10 -> 23
A11: 9 | B11: Hardening | C11: Airplane mode + live co-edit | D11: T9.1, T9.2 | E11: =SUMIF(Backlog!A:A,A11,Backlog!G:G) -> 2 | F11: =F10+E11 -> 25
A12: 10 | B12: Hardening | C12: TestFlight / Play internal | D12: T10.1, T10.2, T10.3, T10.4, T10.5, T10.6 | E12: =SUMIF(Backlog!A:A,A12,Backlog!G:G) -> 3 | F12: =F11+E12 -> 28
A13: 11 | B13: Signals | C13: Friction + intention + suggestions visible | D13: T11.1, T11.2, T11.3, T11.4, T11.5, T11.6, T11.7 | E13: =SUMIF(Backlog!A:A,A13,Backlog!G:G) -> 2.5 | F13: =F12+E13 -> 30.5
A14: 12 | B14: Themes | C14: Trip title themes the share card | D14: T12.1, T12.2, T12.3 | E14: =SUMIF(Backlog!A:A,A14,Backlog!G:G) -> 1.25 | F14: =F13+E14 -> 31.75
A15: 13 | B15: I18n | C15: RTL-correct + script-ready (no translations yet) | D15: T13.1-T13.6 | E15: =SUMIF(Backlog!A:A,A15,Backlog!G:G) -> 2.5 | F15: =F14+E15 -> 34.25
D16: TOTAL | E16: =SUM(E2:E15) -> 34.25

Sheet Sprint summary
A1: Sprint | B1: Focus | C1: Tasks | D1: Goal | E1: Effort (d)
A2: A: Foundations | B2: Backend + app_core stood up | C2: T1.1-T1.7, T2.1-T2.7 | D2: Supabase live with schema+RLS+auth; Flutter shell with design system, Drift, analytics. | E2: =SUMIF(Backlog!G:G,A2,Backlog!E:E) -> 0
A3: B: Core split flow | B3: The SplitTrip loop end-to-end | C3: T3.1-T3.3, T4.1-T4.3, T5.1-T5.3, T6.1-T6.5 | D3: Create/join trips, add multi-currency expenses, correct minimal settle-up, mark/confirm. | E3: =SUMIF(Backlog!G:G,A3,Backlog!E:E) -> 0
A4: C: Growth + ship | B4: Snapshot, solo, offline, ship | C4: T7.1-T7.2, T8.1, T9.1-T9.2, T10.1-T10.6 | D4: Branded share + solo capture + offline sync; QA; ship to TestFlight / Play internal. | E4: =SUMIF(Backlog!G:G,A4,Backlog!E:E) -> 0
D5: TOTAL | E5: =SUM(E2:E4) -> 0
A7: Note: Sprints are rough capacity buckets. Use the Slice column on the Backlog as the day-to-day execution order.

Sheet Acceptance coverage
A1: # | B1: Wave-1 'done' criterion | C1: Covered by
A2: AC1 | B2: Solo user: create trip, capture, share branded snapshot | C2: T3.2/T3.3, T8.1, T7.1/T7.2
A3: AC2 | B3: Group: invite/join (incl. mid-trip), custom-split multi-currency expenses, minimal settle-up, mark/confirm | C3: T3.3, T4.2/T4.3, T5.1-T5.3, T6.3-T6.5
A4: AC3 | B4: Private by default, RLS-enforced (non-member can't read) | C4: T1.2, T1.5, T1.6, T10.4
A5: AC4 | B5: Works offline, syncs on reconnect | C5: T2.5, T9.1, T9.2
A6: AC5 | B6: Settle-up + FX math pass unit tests | C6: T1.7, T5.3, T6.1, T6.2
A7: AC6 | B7: All analytics events fire | C7: T2.6, T3.3, T4.2/T4.3, T5.3, T6.4/T6.5, T7.2, T10.3
A8: AC7 | B8: Product signals live: friction events, intention doors, suggestions (RLS-verified) | C8: T11.1-T11.7
