Workbook

Sheet Summary
A1: Vamo — financial summary (selected scenario)
A2: Toggle Assumptions!B4 to compare Conservative / Base / Upside.
A4: Metric | B4: Year 1 | C4: Year 2 | D4: Year 3
A5: Net revenue | B5: =SUM(Model!L4:L15) -> 11296.051 | C5: =SUM(Model!L16:L27) -> 54975.666 | D5: =SUM(Model!L28:L39) -> 183265.97
A6: Total cost | B6: =SUM(Model!Q4:Q15) -> 15656.169 | C6: =SUM(Model!Q16:Q27) -> 37403.757 | D6: =SUM(Model!Q28:Q39) -> 92532.403
A7: EBITDA | B7: =SUM(Model!R4:R15) -> -4360.1178 | C7: =SUM(Model!R16:R27) -> 17571.909 | D7: =SUM(Model!R28:R39) -> 90733.565
A8: Paying users (year end) | B8: =Model!J15 -> 436.815 | C8: =Model!J27 -> 1508.0666 | D8: =Model!J39 -> 4358.9944
A9: MAU (year end) | B9: =Model!H15 -> 11875.321 | C9: =Model!H27 -> 37513.63 | D9: =Model!H39 -> 106231.18
A10: Cumulative cash (year end) | B10: =Model!S15 -> -4360.1178 | C10: =Model!S27 -> 13211.791 | D10: =Model!S39 -> 103945.36
A11: Lowest cash point in year | B11: =MIN(Model!S4:S15) -> -4479.5988 | C11: =MIN(Model!S16:S27) -> -4122.8925 | D11: =MIN(Model!S28:S39) -> 17206.684
A13: EBITDA-positive from month | B13: =MIN(Model!T4:T39) -> 11 | C13: 9999 = not yet positive in 36 mo
A14: Peak funding need ($, pre-capital) | B14: =-MIN(Model!S4:S39) -> 4479.5988
A16: Starting capital (EUR 10k) | B16: =Assumptions!$E$27 -> 10800
A17: Cash balance, year-end (incl. capital) | B17: =Assumptions!$E$27+Model!S15 -> 6439.8822 | C17: =Assumptions!$E$27+Model!S27 -> 24011.791 | D17: =Assumptions!$E$27+Model!S39 -> 114745.36
A18: Lowest cash balance (incl. capital) | B18: =Assumptions!$E$27+MIN(Model!S4:S39) -> 6320.4012
A19: Fully funded by the EUR 10k? | B19: =IF(B18>0,"Yes - with buffer","No") -> Yes - with buffer

Sheet Assumptions
A1: Vamo — Financial Model - Assumptions
A2: Edit blue cells. Switch the scenario in B4 to recompute the whole model.
A4: Scenario | B4: Base
A6: Assumption | B6: Conservative | C6: Base | D6: Upside | E6: Selected | F6: Unit / note
A7: Organic installs, month 1 | B7: 700 | C7: 1300 | D7: 2200 | E7: =INDEX(B7:D7,MATCH($B$4,$B$6:$D$6,0)) -> 1300 | F7: installs/mo: ASO + any-trip (incl. commute) + solo discovery
A8: Organic MoM growth | B8: 0.06 | C8: 0.09 | D8: 0.13 | E8: =INDEX(B8:D8,MATCH($B$4,$B$6:$D$6,0)) -> 0.09 | F8: month-over-month
A9: Viral coefficient | B9: 0.1 | C9: 0.14 | D9: 0.2 | E9: =INDEX(B9:D9,MATCH($B$4,$B$6:$D$6,0)) -> 0.14 | F9: new joiners/active/mo: branded social shares + join-a-trip + bill invites
A10: Activation rate | B10: 0.55 | C10: 0.6 | D10: 0.65 | E10: =INDEX(B10:D10,MATCH($B$4,$B$6:$D$6,0)) -> 0.6 | F10: install -> active member
A11: Monthly dormancy | B11: 0.2 | C11: 0.16 | D11: 0.13 | E11: =INDEX(B11:D11,MATCH($B$4,$B$6:$D$6,0)) -> 0.16 | F11: active base decay / mo (episodic travel)
A12: Free -> paid conversion | B12: 0.018 | C12: 0.028 | D12: 0.042 | E12: =INDEX(B12:D12,MATCH($B$4,$B$6:$D$6,0)) -> 0.028 | F12: of installs (freemium median ~2.2%)
A13: Monthly paying churn | B13: 0.1 | C13: 0.08 | D13: 0.06 | E13: =INDEX(B13:D13,MATCH($B$4,$B$6:$D$6,0)) -> 0.08 | F13: consumer app avg ~9%/mo
A14: Voyager price ($/mo) | B14: 4 | C14: 4 | D14: 4 | E14: =INDEX(B14:D14,MATCH($B$4,$B$6:$D$6,0)) -> 4 | F14: Voyager mid tier price
A15: Pioneer price ($/mo) | B15: 11 | C15: 11 | D15: 11 | E15: =INDEX(B15:D15,MATCH($B$4,$B$6:$D$6,0)) -> 11 | F15: Pioneer top tier: action-cam, replay, Orbit+Constellations
A16: Pioneer share of payers | B16: 0.12 | C16: 0.2 | D16: 0.3 | E16: =INDEX(B16:D16,MATCH($B$4,$B$6:$D$6,0)) -> 0.2 | F16: % of paying users on Pioneer (rest on Voyager)
A17: Voyager opex ($/mo) | B17: 0.9 | C17: 0.9 | D17: 0.9 | E17: =INDEX(B17:D17,MATCH($B$4,$B$6:$D$6,0)) -> 0.9 | F17: render+storage+map per Voyager payer
A18: Pioneer opex ($/mo) | B18: 3.1 | C18: 3.1 | D18: 3.1 | E18: =INDEX(B18:D18,MATCH($B$4,$B$6:$D$6,0)) -> 3.1 | F18: action-cam storage+render per Pioneer payer
... A27: Starting capital ($) | B27: 10800 | C27: 10800 | D27: 10800 | E27: =INDEX(B27:D27,MATCH($B$4,$B$6:$D$6,0)) -> 10800 | F27: founder's EUR 10k injection (~$10,800 at EUR/USD 1.08)
A28: Operator track (B2B) — active from the Wave-3 gate; Conservative = gate failed (consumer-only)
A29: Operator launch month | B29: 9999 | C29: 20 | D29: 16 | E29: =INDEX(B29:D29,MATCH($B$4,$B$6:$D$6,0)) -> 20 | F29: month operator onboarding starts (post Wave-3 gate); 9999 = never
A30: New operators / month | B30: 0 | C30: 2 | D30: 5 | E30: =INDEX(B30:D30,MATCH($B$4,$B$6:$D$6,0)) -> 2 | F30: tour guides & operators onboarded/mo (founder-led sales)
A31: Operator monthly churn | B31: 0.03 | C31: 0.03 | D31: 0.02 | E31: =INDEX(B31:D31,MATCH($B$4,$B$6:$D$6,0)) -> 0.03 | F31: B2B churn (annual contracts later)
A32: Revenue per operator ($/mo) | B32: 0 | C32: 120 | D32: 180 | E32: =INDEX(B32:D32,MATCH($B$4,$B$6:$D$6,0)) -> 120 | F32: per-trip/per-seat blended; web billing - no app store fee
A33: Operator opex ($/mo) | B33: 0 | C33: 14 | D33: 18 | E33: =INDEX(B33:D33,MATCH($B$4,$B$6:$D$6,0)) -> 14 | F33: audio/media storage + hosting + support per operator

Sheet Model
A1: Vamo — 36-month operating model (selected scenario)
A3: Month | B3: Paid $ | C3: Paid inst. | D3: Organic inst. | E3: Viral inst. | F3: New installs | G3: New actives | H3: MAU | I3: New paying | J3: Paying users | K3: Gross rev | L3: Net rev | M3: Infra+tier | N3: Marketing | O3: Contractors | P3: Fixed | Q3: Total cost | R3: EBITDA | S3: Cum. cash | T3: be_helper | U3: Operators | V3: Oper. net rev | W3: Oper. opex
A4: 1 | B4: =Assumptions!$E$20 -> 250 | C4: =B4/Assumptions!$E$22 -> 71.428571 | D4: =Assumptions!$E$7*(1+Assumptions!$E$8)^(A4-1) -> 1300 | E4: 0 | F4: =C4+D4+E4 -> 1371.4286 | G4: =F4*Assumptions!$E$10 -> 822.85714 | H4: =G4 -> 822.85714 | I4: =G4*Assumptions!$E$12 -> 23.04 | J4: =I4 -> 23.04 | K4: =J4*(Assumptions!$E$14*(1-Assumptions!$E$16)+Assumptions!$E$15*Assumptions!$E$16) -> 124.416 | L4: =K4*(1-Assumptions!$E$19)+V4 -> 105.7536 | M4: =H4*Assumptions!$E$23+J4*(Assumptions!$E$17*(1-Assumptions!$E$16)+Assumptions!$E$18*Assumptions!$E$16) -> 55.559314 | N4: =B4 -> 250 | O4: =IF(A4>=Assumptions!$E$25,Assumptions!$E$26,0) -> 0 | P4: =Assumptions!$E$24 -> 520 | Q4: =M4+N4+O4+P4+W4 -> 825.55931 | R4: =L4-Q4 -> -719.80571 | S4: =R4 -> -719.80571 | T4: =IF(R4>0,A4,9999) -> 9999 | U4: =IF(A4>=Assumptions!$E$29,Assumptions!$E$30,0) -> 0 | V4: =U4*Assumptions!$E$32 -> 0 | W4: =U4*Assumptions!$E$33 -> 0
A5: 2 | B5: =B4*(1+Assumptions!$E$21) -> 262.5 | C5: =B5/Assumptions!$E$22 -> 75 | D5: =Assumptions!$E$7*(1+Assumptions!$E$8)^(A5-1) -> 1417 | E5: =H4*Assumptions!$E$9 -> 115.2 | F5: =C5+D5+E5 -> 1607.2 | G5: =F5*Assumptions!$E$10 -> 964.32 | H5: =H4*(1-Assumptions!$E$11)+G5 -> 1655.52 | I5: =G5*Assumptions!$E$12 -> 27.00096 | J5: =J4*(1-Assumptions!$E$13)+I5 -> 48.19776 | K5: =J5*(Assumptions!$E$14*(1-Assumptions!$E$16)+Assumptions!$E$15*Assumptions!$E$16) -> 260.2679 | L5: =K5*(1-Assumptions!$E$19)+V5 -> 221.22772 | M5: =H5*Assumptions!$E$23+J5*(Assumptions!$E$17*(1-Assumptions!$E$16)+Assumptions!$E$18*Assumptions!$E$16) -> 114.2506 | N5: =B5 -> 262.5 | O5: =IF(A5>=Assumptions!$E$25,Assumptions!$E$26,0) -> 0 | P5: =Assumptions!$E$24 -> 520 | Q5: =M5+N5+O5+P5+W5 -> 896.7506 | R5: =L5-Q5 -> -675.52288 | S5: =S4+R5 -> -1395.3286 | T5: =IF(R5>0,A5,9999) -> 9999 | U5: =IF(A5>=Assumptions!$E$29,U4*(1-Assumptions!$E$31)+Assumptions!$E$30,0) -> 0 | V5: =U5*Assumptions!$E$32 -> 0 | W5: =U5*Assumptions!$E$33 -> 0
A6: 3 | B6: =B5*(1+Assumptions!$E$21) -> 275.625 | C6: =B6/Assumptions!$E$22 -> 78.75 | D6: =Assumptions!$E$7*(1+Assumptions!$E$8)^(A6-1) -> 1544.53 | E6: =H5*Assumptions!$E$9 -> 231.7728 | F6: =C6+D6+E6 -> 1855.0528 | G6: =F6*Assumptions!$E$10 -> 1113.0317 | H6: =H5*(1-Assumptions!$E$11)+G6 -> 2503.6685 | I6: =G6*Assumptions!$E$12 -> 31.164887 | J6: =J5*(1-Assumptions!$E$13)+I6 -> 75.506826 | K6: =J6*(Assumptions!$E$14*(1-Assumptions!$E$16)+Assumptions!$E$15*Assumptions!$E$16) -> 407.73686 | L6: =K6*(1-Assumptions!$E$19)+V6 -> 346.57633 | M6: =H6*Assumptions!$E$23+J6*(Assumptions!$E$17*(1-Assumptions!$E$16)+Assumptions!$E$18*Assumptions!$E$16) -> 176.2892 | N6: =B6 -> 275.625 | O6: =IF(A6>=Assumptions!$E$25,Assumptions!$E$26,0) -> 0 | P6: =Assumptions!$E$24 -> 520 | Q6: =M6+N6+O6+P6+W6 -> 971.9142 | R6: =L6-Q6 -> -625.33787 | S6: =S5+R6 -> -2020.6665 | T6: =IF(R6>0,A6,9999) -> 9999 | U6: =IF(A6>=Assumptions!$E$29,U5*(1-Assumptions!$E$31)+Assumptions!$E$30,0) -> 0 | V6: =U6*Assumptions!$E$32 -> 0 | W6: =U6*Assumptions!$E$33 -> 0
A7: 4 | B7: =B6*(1+Assumptions!$E$21) -> 289.40625 | C7: =B7/Assumptions!$E$22 -> 82.6875 | D7: =Assumptions!$E$7*(1+Assumptions!$E$8)^(A7-1) -> 1683.5377 | E7: =H6*Assumptions!$E$9 -> 350.51359 | F7: =C7+D7+E7 -> 2116.7388 | G7: =F7*Assumptions!$E$10 -> 1270.0433 | H7: =H6*(1-Assumptions!$E$11)+G7 -> 3373.1248 | I7: =G7*Assumptions!$E$12 -> 35.561212 | J7: =J6*(1-Assumptions!$E$13)+I7 -> 105.02749 | K7: =J7*(Assumptions!$E$14*(1-Assumptions!$E$16)+Assumptions!$E$15*Assumptions!$E$16) -> 567.14846 | L7: =K7*(1-Assumptions!$E$19)+V7 -> 482.07619 | M7: =H7*Assumptions!$E$23+J7*(Assumptions!$E$17*(1-Assumptions!$E$16)+Assumptions!$E$18*Assumptions!$E$16) -> 241.93058 | N7: =B7 -> 289.40625 | O7: =IF(A7>=Assumptions!$E$25,Assumptions!$E$26,0) -> 0 | P7: =Assumptions!$E$24 -> 520 | Q7: =M7+N7+O7+P7+W7 -> 1051.3368 | R7: =L7-Q7 -> -569.26065 | S7: =S6+R7 -> -2589.9271 | T7: =IF(R7>0,A7,9999) -> 9999 | U7: =IF(A7>=Assumptions!$E$29,U6*(1-Assumptions!$E$31)+Assumptions!$E$30,0) -> 0 | V7: =U7*Assumptions!$E$32 -> 0 | W7: =U7*Assumptions!$E$33 -> 0
A8: 5 | B8: =B7*(1+Assumptions!$E$21) -> 303.87656 | C8: =B8/Assumptions!$E$22 -> 86.821875 | D8: =Assumptions!$E$7*(1+Assumptions!$E$8)^(A8-1) -> 1835.0561 | E8: =H7*Assumptions!$E$9 -> 472.23747 | F8: =C8+D8+E8 -> 2394.1154 | G8: =F8*Assumptions!$E$10 -> 1436.4693 | H8: =H7*(1-Assumptions!$E$11)+G8 -> 4269.8941 | I8: =G8*Assumptions!$E$12 -> 40.221139 | J8: =J7*(1-Assumptions!$E$13)+I8 -> 136.84643 | K8: =J8*(Assumptions!$E$14*(1-Assumptions!$E$16)+Assumptions!$E$15*Assumptions!$E$16) -> 738.97073 | L8: =K8*(1-Assumptions!$E$19)+V8 -> 628.12512 | M8: =H8*Assumptions!$E$23+J8*(Assumptions!$E$17*(1-Assumptions!$E$16)+Assumptions!$E$18*Assumptions!$E$16) -> 311.47104 | N8: =B8 -> 303.87656 | O8: =IF(A8>=Assumptions!$E$25,Assumptions!$E$26,0) -> 0 | P8: =Assumptions!$E$24 -> 520 | Q8: =M8+N8+O8+P8+W8 -> 1135.3476 | R8: =L8-Q8 -> -507.22248 | S8: =S7+R8 -> -3097.1496 | T8: =IF(R8>0,A8,9999) -> 9999 | U8: =IF(A8>=Assumptions!$E$29,U7*(1-Assumptions!$E$31)+Assumptions!$E$30,0) -> 0 | V8: =U8*Assumptions!$E$32 -> 0 | W8: =U8*Assumptions!$E$33 -> 0
A9: 6 | B9: =B8*(1+Assumptions!$E$21) -> 319.07039 | C9: =B9/Assumptions!$E$22 -> 91.162969 | D9: =Assumptions!$E$7*(1+Assumptions!$E$8)^(A9-1) -> 2000.2111 | E9: =H8*Assumptions!$E$9 -> 597.78517 | F9: =C9+D9+E9 -> 2689.1593 | G9: =F9*Assumptions!$E$10 -> 1613.4956 | H9: =H8*(1-Assumptions!$E$11)+G9 -> 5200.2066 | I9: =G9*Assumptions!$E$12 -> 45.177876 | J9: =J8*(1-Assumptions!$E$13)+I9 -> 171.07659 | K9: =J9*(Assumptions!$E$14*(1-Assumptions!$E$16)+Assumptions!$E$15*Assumptions!$E$16) -> 923.8136 | L9: =K9*(1-Assumptions!$E$19)+V9 -> 785.24156 | M9: =H9*Assumptions!$E$23+J9*(Assumptions!$E$17*(1-Assumptions!$E$16)+Assumptions!$E$18*Assumptions!$E$16) -> 385.24883 | N9: =B9 -> 319.07039 | O9: =IF(A9>=Assumptions!$E$25,Assumptions!$E$26,0) -> 0 | P9: =Assumptions!$E$24 -> 520 | Q9: =M9+N9+O9+P9+W9 -> 1224.3192 | R9: =L9-Q9 -> -439.07766 | S9: =S8+R9 -> -3536.2273 | T9: =IF(R9>0,A9,9999) -> 9999 | U9: =IF(A9>=Assumptions!$E$29,U8*(1-Assumptions!$E$31)+Assumptions!$E$30,0) -> 0 | V9: =U9*Assumptions!$E$32 -> 0 | W9: =U9*Assumptions!$E$33 -> 0
A10: 7 | B10: =B9*(1+Assumptions!$E$21) -> 335.02391 | C10: =B10/Assumptions!$E$22 -> 95.721117 | D10: =Assumptions!$E$7*(1+Assumptions!$E$8)^(A10-1) -> 2180.2301 | E10: =H9*Assumptions!$E$9 -> 728.02892 | F10: =C10+D10+E10 -> 3003.9802 | G10: =F10*Assumptions!$E$10 -> 1802.3881 | H10: =H9*(1-Assumptions!$E$11)+G10 -> 6170.5617 | I10: =G10*Assumptions!$E$12 -> 50.466867 | J10: =J9*(1-Assumptions!$E$13)+I10 -> 207.85733 | K10: =J10*(Assumptions!$E$14*(1-Assumptions!$E$16)+Assumptions!$E$15*Assumptions!$E$16) -> 1122.4296 | L10: =K10*(1-Assumptions!$E$19)+V10 -> 954.06516 | M10: =H10*Assumptions!$E$23+J10*(Assumptions!$E$17*(1-Assumptions!$E$16)+Assumptions!$E$18*Assumptions!$E$16) -> 463.64568 | N10: =B10 -> 335.02391 | O10: =IF(A10>=Assumptions!$E$25,Assumptions!$E$26,0) -> 0 | P10: =Assumptions!$E$24 -> 520 | Q10: =M10+N10+O10+P10+W10 -> 1318.6696 | R10: =L10-Q10 -> -364.60443 | S10: =S9+R10 -> -3900.8317 | T10: =IF(R10>0,A10,9999) -> 9999 | U10: =IF(A10>=Assumptions!$E$29,U9*(1-Assumptions!$E$31)+Assumptions!$E$30,0) -> 0 | V10: =U10*Assumptions!$E$32 -> 0 | W10: =U10*Assumptions!$E$33 -> 0
A11: 8 | B11: =B10*(1+Assumptions!$E$21) -> 351.77511 | C11: =B11/Assumptions!$E$22 -> 100.50717 | D11: =Assumptions!$E$7*(1+Assumptions!$E$8)^(A11-1) -> 2376.4509 | E11: =H10*Assumptions!$E$9 -> 863.87863 | F11: =C11+D11+E11 -> 3340.8367 | G11: =F11*Assumptions!$E$10 -> 2004.502 | H11: =H10*(1-Assumptions!$E$11)+G11 -> 7187.7738 | I11: =G11*Assumptions!$E$12 -> 56.126056 | J11: =J10*(1-Assumptions!$E$13)+I11 -> 247.3548 | K11: =J11*(Assumptions!$E$14*(1-Assumptions!$E$16)+Assumptions!$E$15*Assumptions!$E$16) -> 1335.7159 | L11: =K11*(1-Assumptions!$E$19)+V11 -> 1135.3585 | M11: =H11*Assumptions!$E$23+J11*(Assumptions!$E$17*(1-Assumptions!$E$16)+Assumptions!$E$18*Assumptions!$E$16) -> 547.08865 | N11: =B11 -> 351.77511 | O11: =IF(A11>=Assumptions!$E$25,Assumptions!$E$26,0) -> 0 | P11: =Assumptions!$E$24 -> 520 | Q11: =M11+N11+O11+P11+W11 -> 1418.8638 | R11: =L11-Q11 -> -283.50521 | S11: =S10+R11 -> -4184.3369 | T11: =IF(R11>0,A11,9999) -> 9999 | U11: =IF(A11>=Assumptions!$E$29,U10*(1-Assumptions!$E$31)+Assumptions!$E$30,0) -> 0 | V11: =U11*Assumptions!$E$32 -> 0 | W11: =U11*Assumptions!$E$33 -> 0
A12: 9 | B12: =B11*(1+Assumptions!$E$21) -> 369.36386 | C12: =B12/Assumptions!$E$22 -> 105.53253 | D12: =Assumptions!$E$7*(1+Assumptions!$E$8)^(A12-1) -> 2590.3314 | E12: =H11*Assumptions!$E$9 -> 1006.2883 | F12: =C12+D12+E12 -> 3702.1523 | G12: =F12*Assumptions!$E$10 -> 2221.2914 | H12: =H11*(1-Assumptions!$E$11)+G12 -> 8259.0214 | I12: =G12*Assumptions!$E$12 -> 62.196159 | J12: =J11*(1-Assumptions!$E$13)+I12 -> 289.76258 | K12: =J12*(Assumptions!$E$14*(1-Assumptions!$E$16)+Assumptions!$E$15*Assumptions!$E$16) -> 1564.7179 | L12: =K12*(1-Assumptions!$E$19)+V12 -> 1330.0102 | M12: =H12*Assumptions!$E$23+J12*(Assumptions!$E$17*(1-Assumptions!$E$16)+Assumptions!$E$18*Assumptions!$E$16) -> 636.05249 | N12: =B12 -> 369.36386 | O12: =IF(A12>=Assumptions!$E$25,Assumptions!$E$26,0) -> 0 | P12: =Assumptions!$E$24 -> 520 | Q12: =M12+N12+O12+P12+W12 -> 1525.4164 | R12: =L12-Q12 -> -195.40613 | S12: =S11+R12 -> -4379.743 | T12: =IF(R12>0,A12,9999) -> 9999 | U12: =IF(A12>=Assumptions!$E$29,U11*(1-Assumptions!$E$31)+Assumptions!$E$30,0) -> 0 | V12: =U12*Assumptions!$E$32 -> 0 | W12: =U12*Assumptions!$E$33 -> 0
A13: 10 | B13: =B12*(1+Assumptions!$E$21) -> 387.83205 | C13: =B13/Assumptions!$E$22 -> 110.80916 | D13: =Assumptions!$E$7*(1+Assumptions!$E$8)^(A13-1) -> 2823.4613 | E13: =H12*Assumptions!$E$9 -> 1156.263 | F13: =C13+D13+E13 -> 4090.5334 | G13: =F13*Assumptions!$E$10 -> 2454.32 | H13: =H12*(1-Assumptions!$E$11)+G13 -> 9391.898 | I13: =G13*Assumptions!$E$12 -> 68.720961 | J13: =J12*(1-Assumptions!$E$13)+I13 -> 335.30253 | K13: =J13*(Assumptions!$E$14*(1-Assumptions!$E$16)+Assumptions!$E$15*Assumptions!$E$16) -> 1810.6337 | L13: =K13*(1-Assumptions!$E$19)+V13 -> 1539.0386 | M13: =H13*Assumptions!$E$23+J13*(Assumptions!$E$17*(1-Assumptions!$E$16)+Assumptions!$E$18*Assumptions!$E$16) -> 731.06233 | N13: =B13 -> 387.83205 | O13: =IF(A13>=Assumptions!$E$25,Assumptions!$E$26,0) -> 0 | P13: =Assumptions!$E$24 -> 520 | Q13: =M13+N13+O13+P13+W13 -> 1638.8944 | R13: =L13-Q13 -> -99.855765 | S13: =S12+R13 -> -4479.5988 | T13: =IF(R13>0,A13,9999) -> 9999 | U13: =IF(A13>=Assumptions!$E$29,U12*(1-Assumptions!$E$31)+Assumptions!$E$30,0) -> 0 | V13: =U13*Assumptions!$E$32 -> 0 | W13: =U13*Assumptions!$E$33 -> 0
A14: 11 | B14: =B13*(1+Assumptions!$E$21) -> 407.22366 | C14: =B14/Assumptions!$E$22 -> 116.34962 | D14: =Assumptions!$E$7*(1+Assumptions!$E$8)^(A14-1) -> 3077.5728 | E14: =H13*Assumptions!$E$9 -> 1314.8657 | F14: =C14+D14+E14 -> 4508.7881 | G14: =F14*Assumptions!$E$10 -> 2705.2729 | H14: =H13*(1-Assumptions!$E$11)+G14 -> 10594.467 | I14: =G14*Assumptions!$E$12 -> 75.74764 | J14: =J13*(1-Assumptions!$E$13)+I14 -> 384.22597 | K14: =J14*(Assumptions!$E$14*(1-Assumptions!$E$16)+Assumptions!$E$15*Assumptions!$E$16) -> 2074.8202 | L14: =K14*(1-Assumptions!$E$19)+V14 -> 1763.5972 | M14: =H14*Assumptions!$E$23+J14*(Assumptions!$E$17*(1-Assumptions!$E$16)+Assumptions!$E$18*Assumptions!$E$16) -> 832.69681 | N14: =B14 -> 407.22366 | O14: =IF(A14>=Assumptions!$E$25,Assumptions!$E$26,0) -> 0 | P14: =Assumptions!$E$24 -> 520 | Q14: =M14+N14+O14+P14+W14 -> 1759.9205 | R14: =L14-Q14 -> 3.6767289 | S14: =S13+R14 -> -4475.9221 | T14: =IF(R14>0,A14,9999) -> 11 | U14: =IF(A14>=Assumptions!$E$29,U13*(1-Assumptions!$E$31)+Assumptions!$E$30,0) -> 0 | V14: =U14*Assumptions!$E$32 -> 0 | W14: =U14*Assumptions!$E$33 -> 0
A15: 12 | B15: =B14*(1+Assumptions!$E$21) -> 427.58484 | C15: =B15/Assumptions!$E$22 -> 122.1671 | D15: =Assumptions!$E$7*(1+Assumptions!$E$8)^(A15-1) -> 3354.5543 | E15: =H14*Assumptions!$E$9 -> 1483.2254 | F15: =C15+D15+E15 -> 4959.9468 | G15: =F15*Assumptions!$E$10 -> 2975.9681 | H15: =H14*(1-Assumptions!$E$11)+G15 -> 11875.321 | I15: =G15*Assumptions!$E$12 -> 83.327107 | J15: =J14*(1-Assumptions!$E$13)+I15 -> 436.815 | K15: =J15*(Assumptions!$E$14*(1-Assumptions!$E$16)+Assumptions!$E$15*Assumptions!$E$16) -> 2358.801 | L15: =K15*(1-Assumptions!$E$19)+V15 -> 2004.9808 | M15: =H15*Assumptions!$E$23+J15*(Assumptions!$E$17*(1-Assumptions!$E$16)+Assumptions!$E$18*Assumptions!$E$16) -> 941.59171 | N15: =B15 -> 427.58484 | O15: =IF(A15>=Assumptions!$E$25,Assumptions!$E$26,0) -> 0 | P15: =Assumptions!$E$24 -> 520 | Q15: =M15+N15+O15+P15+W15 -> 1889.1766 | R15: =L15-Q15 -> 115.80429 | S15: =S14+R15 -> -4360.1178 | T15: =IF(R15>0,A15,9999) -> 12 | U15: =IF(A15>=Assumptions!$E$29,U14*(1-Assumptions!$E$31)+Assumptions!$E$30,0) -> 0 | V15: =U15*Assumptions!$E$32 -> 0 | W15: =U15*Assumptions!$E$33 -> 0
A16: 13 | B16: =B15*(1+Assumptions!$E$21) -> 448.96408 | C16: =B16/Assumptions!$E$22 -> 128.27545 | D16: =Assumptions!$E$7*(1+Assumptions!$E$8)^(A16-1) -> 3656.4642 | E16: =H15*Assumptions!$E$9 -> 1662.5449 | F16: =C16+D16+E16 -> 5447.2845 | G16: =F16*Assumptions!$E$10 -> 3268.3707 | H16: =H15*(1-Assumptions!$E$11)+G16 -> 13243.64 | I16: =G16*Assumptions!$E$12 -> 91.51438 | J16: =J15*(1-Assumptions!$E$13)+I16 -> 493.38418 | K16: =J16*(Assumptions!$E$14*(1-Assumptions!$E$16)+Assumptions!$E$15*Assumptions!$E$16) -> 2664.2746 | L16: =K16*(1-Assumptions!$E$19)+V16 -> 2264.6334 | M16: =H16*Assumptions!$E$23+J16*(Assumptions!$E$17*(1-Assumptions!$E$16)+Assumptions!$E$18*Assumptions!$E$16) -> 1058.444 | N16: =B16 -> 448.96408 | O16: =IF(A16>=Assumptions!$E$25,Assumptions!$E$26,0) -> 0 | P16: =Assumptions!$E$24 -> 520 | Q16: =M16+N16+O16+P16+W16 -> 2027.4081 | R16: =L16-Q16 -> 237.2253 | S16: =S15+R16 -> -4122.8925 | T16: =IF(R16>0,A16,9999) -> 13 | U16: =IF(A16>=Assumptions!$E$29,U15*(1-Assumptions!$E$31)+Assumptions!$E$30,0) -> 0 | V16: =U16*Assumptions!$E$32 -> 0 | W16: =U16*Assumptions!$E$33 -> 0
... A39: 36 | B39: =B38*(1+Assumptions!$E$21) -> 1379.0038 | C39: =B39/Assumptions!$E$22 -> 394.0011 | D39: =Assumptions!$E$7*(1+Assumptions!$E$8)^(A39-1) -> 26538.158 | E39: =H38*Assumptions!$E$9 -> 13647.256 | F39: =C39+D39+E39 -> 40579.415 | G39: =F39*Assumptions!$E$10 -> 24347.649 | H39: =H38*(1-Assumptions!$E$11)+G39 -> 106231.18 | I39: =G39*Assumptions!$E$12 -> 681.73417 | J39: =J38*(1-Assumptions!$E$13)+I39 -> 4358.9944 | K39: =J39*(Assumptions!$E$14*(1-Assumptions!$E$16)+Assumptions!$E$15*Assumptions!$E$16) -> 23538.57 | L39: =K39*(1-Assumptions!$E$19)+V39 -> 23241.176 | M39: =H39*Assumptions!$E$23+J39*(Assumptions!$E$17*(1-Assumptions!$E$16)+Assumptions!$E$18*Assumptions!$E$16) -> 9027.988 | N39: =B39 -> 1379.0038 | O39: =IF(A39>=Assumptions!$E$25,Assumptions!$E$26,0) -> 0 | P39: =Assumptions!$E$24 -> 520 | Q39: =M39+N39+O39+P39+W39 -> 11304.221 | R39: =L39-Q39 -> 11936.955 | S39: =S38+R39 -> 103945.36 | T39: =IF(R39>0,A39,9999) -> 36 | U39: =IF(A39>=Assumptions!$E$29,U38*(1-Assumptions!$E$31)+Assumptions!$E$30,0) -> 26.94493 | V39: =U39*Assumptions!$E$32 -> 3233.3916 | W39: =U39*Assumptions!$E$33 -> 377.22903

Sheet UnitEconomics
A1: Unit economics (selected scenario)
A3: ARPU (paying), $/mo | B3: =(Assumptions!$E$14*(1-Assumptions!$E$16)+Assumptions!$E$15*Assumptions!$E$16) -> 5.4
A4: App store fee | B4: =Assumptions!$E$19 -> 0.15
A5: Net ARPU, $/mo | B5: =B3*(1-B4) -> 4.59
A6: Monthly paying churn | B6: =Assumptions!$E$13 -> 0.08
A7: Avg paying lifetime, months | B7: =1/B6 -> 12.5
A8: Gross LTV, $ | B8: =B5*B7 -> 57.375
A9: Premium opex per payer (life), $ | B9: =(Assumptions!$E$17*(1-Assumptions!$E$16)+Assumptions!$E$18*Assumptions!$E$16)*B7 -> 16.75
A10: Net LTV, $ | B10: =B8-B9 -> 40.625
A11: Blended CAC, $ (mktg / new paying) | B11: =SUM(Model!N4:N39)/SUM(Model!I4:I39) -> 3.0672321
A12: Paid-only CAC, $ (CPI / conv) | B12: =Assumptions!$E$22/Assumptions!$E$12 -> 125
A13: LTV : CAC (blended) | B13: =B10/B11 -> 13.244841
A14: Target: LTV:CAC ≥ 3.0x, payback < 12 mo. The invite loop is what holds blended CAC low. | B14: =B11/B5 -> 0.66824229
